quantrm_xd/Option.py
quantrm_xd/VaR.py
quantrm_xd/__init__.py
quantrm_xd/calculation.py
quantrm_xd/cov_matrix.py
quantrm_xd/linear_regression.py
quantrm_xd/optimal_portfolio.py
quantrm_xd/risk_attribution.py
quantrm_xd/risk_parity.py
quantrm_xd/simulation.py
quantrm_xd-0.9.2.dist-info/METADATA
quantrm_xd-0.9.2.dist-info/WHEEL
quantrm_xd-0.9.2.dist-info/top_level.txt
quantrm_xd-0.9.2.dist-info/RECORD
